jsonrpclib/SimpleJSONRPCServer.py
jsonrpclib/__init__.py
jsonrpclib/config.py
jsonrpclib/history.py
jsonrpclib/jsonclass.py
jsonrpclib/jsonlib.py
jsonrpclib/jsonrpc.py
jsonrpclib/threadpool.py
jsonrpclib/utils.py
jsonrpclib_pelix-1.0.0.dist-info/METADATA
jsonrpclib_pelix-1.0.0.dist-info/WHEEL
jsonrpclib_pelix-1.0.0.dist-info/licenses/LICENSE
jsonrpclib_pelix-1.0.0.dist-info/RECORD
