Metadata-Version: 2.4
Name: jsonrpclib-pelix
Version: 1.0.0
Summary: JSON-RPC v2.0 client and server for Python 2.7 and Python 3.6+ usable with Pelix/iPOPO remote services.
Project-URL: Homepage, https://github.com/tcalmant/jsonrpclib/
Project-URL: Issues, https://github.com/tcalmant/jsonrpclib/issues
Project-URL: Documentation, https://jsonrpclib-pelix.readthedocs.io/
Project-URL: Source, https://github.com/tcalmant/jsonrpclib/
Author: Josh Marshall
Author-email: Thomas Calmant <thomas.calmant+github@gmail.com>
License-Expression: Apache-2.0
License-File: LICENSE
Classifier: Development Status :: 5 - Production/Stable
Classifier: Intended Audience :: Developers
Classifier: License :: OSI Approved :: Apache Software License
Classifier: Operating System :: OS Independent
Classifier: Programming Language :: Python :: 2.7
Classifier: Programming Language :: Python :: 3
Classifier: Programming Language :: Python :: 3.6
Classifier: Programming Language :: Python :: 3.7
Classifier: Programming Language :: Python :: 3.8
Classifier: Programming Language :: Python :: 3.9
Classifier: Programming Language :: Python :: 3.10
Classifier: Programming Language :: Python :: 3.11
Classifier: Programming Language :: Python :: 3.12
Classifier: Programming Language :: Python :: 3.13
Classifier: Programming Language :: Python :: 3.14
Requires-Python: >=3.6
